django_http_proxy-0.4.3.dist-info/DESCRIPTION.rst
django_http_proxy-0.4.3.dist-info/METADATA
django_http_proxy-0.4.3.dist-info/metadata.json
django_http_proxy-0.4.3.dist-info/RECORD
django_http_proxy-0.4.3.dist-info/top_level.txt
django_http_proxy-0.4.3.dist-info/WHEEL
httpproxy/__init__.py
httpproxy/_version.py
httpproxy/admin.py
httpproxy/exceptions.py
httpproxy/models.py
httpproxy/recorder.py
httpproxy/views.py
httpproxy/migrations/0001_initial.py
httpproxy/migrations/0002_auto_20160121_1940.py
httpproxy/migrations/__init__.py
